Metadata-Version: 2.1
Name: hits-x
Version: 0.1.3
Summary: Updated and modified from Jeff's version.
License: GNU General Public License v3.0
Author: hukai916
Author-email: 31452631+hukai916@users.noreply.github.com
Requires-Python: >=3.8,<4.0
Classifier: License :: Other/Proprietary License
Classifier: Programming Language :: Python :: 3
Classifier: Programming Language :: Python :: 3.8
Classifier: Programming Language :: Python :: 3.9
Classifier: Programming Language :: Python :: 3.10
Classifier: Programming Language :: Python :: 3.11
Requires-Dist: Pillow (>=9.4.0,<10.0.0)
Requires-Dist: biopython (>=1.81,<2.0)
Requires-Dist: bokeh (>=3.0.3,<4.0.0)
Requires-Dist: ipython (>=8.10.0,<9.0.0)
Requires-Dist: ipywidgets (>=8.0.4,<9.0.0)
Requires-Dist: matplotlib (>=3.7.0,<4.0.0)
Requires-Dist: numpy (>=1.24.2,<2.0.0)
Requires-Dist: pandas (>=1.5.3,<2.0.0)
Requires-Dist: pysam (>=0.20.0,<0.21.0)
Requires-Dist: pyyaml (>=6.0,<7.0)
Requires-Dist: seaborn (>=0.12.2,<0.13.0)
Requires-Dist: statsmodels (>=0.13.5,<0.14.0)
